incr.py
incr-0.1.2.dist-info/LICENSE
incr-0.1.2.dist-info/METADATA
incr-0.1.2.dist-info/WHEEL
incr-0.1.2.dist-info/top_level.txt
incr-0.1.2.dist-info/RECORD
