Metadata-Version: 2.1
Name: incr
Version: 0.1.2
Summary: ++ operator in python
Home-page: https://github.com/alimsk/incr
Author: Ali M
License: UNKNOWN
Platform: UNKNOWN
Requires-Python: >=3.6
